pydbytes/__init__.py
pydbytes-1.0.1.dist-info/METADATA
pydbytes-1.0.1.dist-info/WHEEL
pydbytes-1.0.1.dist-info/top_level.txt
pydbytes-1.0.1.dist-info/RECORD
