Metadata-Version: 2.1
Name: pydbytes
Version: 1.0.1
Summary: A mod
Author: Ayumu
Author-email: Ayumu-1337@proton.me
Classifier: Programming Language :: Python :: 3
Classifier: License :: OSI Approved :: MIT License
Classifier: Operating System :: OS Independent
Requires-Python: >=3.6
